{
  "period_s": 2.2,
  "dt_s": 0.02,
  "transfer_s": 0.35,
  "swing_raise_s": 0.55,
  "swing_advance_s": 0.85,
  "touchdown_s": 0.1,
  "stabilize_s": 0.35,
  "step_length_mm": 16.0,
  "support_push_mm": 10.0,
  "back_swing_mm": 6.0,
  "lift_clearance_mm": 150.0,
  "support_crouch_mm": 24.0,
  "stance_width_mm": 16.0,
  "weight_shift_mm": 28.0,
  "max_com_lateral_mm": 30.0,
  "max_com_forward_mm": 18.0,
  "max_com_cycle_lateral_mm": 40.0,
  "max_com_cycle_forward_mm": 20.0,
  "support_load_ratio": 0.85,
  "support_pose_angle_deg": 1.8,
  "toe_contact_clearance_mm": 8.0,
  "toe_ankle_offset_deg": -12.0,
  "heel_ankle_offset_deg": 6.0,
  "settle_ankle_offset_deg": 2.0,
  "yaw_trim_mm": 1.5,
  "nominal_height_mm": 190.0,
  "zero_blend_ratio": 0.5,
  "servo_limit_deg": 30.0,
  "pid": {
    "kp": 0.72,
    "ki": 0.06,
    "kd": 0.03,
    "integral_limit": 120.0,
    "command_limit": 28.0,
    "estimation_alpha": 0.6
  }
}
